pypuppetdb/QueryBuilder.py
pypuppetdb/__init__.py
pypuppetdb/errors.py
pypuppetdb/types.py
pypuppetdb/utils.py
pypuppetdb/api/__init__.py
pypuppetdb/api/base.py
pypuppetdb/api/command.py
pypuppetdb/api/metadata.py
pypuppetdb/api/metrics.py
pypuppetdb/api/pql.py
pypuppetdb/api/query.py
pypuppetdb/api/status.py
pypuppetdb-3.2.0.data/data/requirements_for_tests/requirements-test.txt
pypuppetdb-3.2.0.dist-info/LICENSE
pypuppetdb-3.2.0.dist-info/METADATA
pypuppetdb-3.2.0.dist-info/WHEEL
pypuppetdb-3.2.0.dist-info/top_level.txt
pypuppetdb-3.2.0.dist-info/RECORD
