Metadata-Version: 2.1
Name: pypuppetdb
Version: 3.2.0
Summary: Library for working with the PuppetDB REST API.
Home-page: https://github.com/voxpupuli/pypuppetdb
Author: Vox Pupuli
Author-email: voxpupuli@groups.io
License: Apache License 2.0
Keywords: puppet puppetdb
Classifier: Development Status :: 5 - Production/Stable
Classifier: Intended Audience :: Developers
Classifier: Natural Language :: English
Classifier: License :: OSI Approved :: Apache Software License
Classifier: Operating System :: POSIX
Classifier: Programming Language :: Python :: 3
Classifier: Programming Language :: Python :: 3.7
Classifier: Programming Language :: Python :: 3.8
Classifier: Programming Language :: Python :: 3.9
Classifier: Programming Language :: Python :: 3.10
Classifier: Programming Language :: Python :: 3.11
Classifier: Topic :: Software Development :: Libraries
Requires-Python: >=3.7.0
License-File: LICENSE
Requires-Dist: requests <3,>=2.28.1
